pyecl/__init__.py
pyecl/constellation.py
pyecl/exceptions.py
pyecl/models.py
pyecl/utils.py
tests/__init__.py
tests/test_binary_object_representation.py
tests/test_constellation.py
tests/test_variable_unit.py
pyecl-0.1.4.dist-info/LICENSE
pyecl-0.1.4.dist-info/METADATA
pyecl-0.1.4.dist-info/WHEEL
pyecl-0.1.4.dist-info/top_level.txt
pyecl-0.1.4.dist-info/RECORD
