Metadata-Version: 2.1
Name: pyecl
Version: 0.1.4
License-File: LICENSE
Requires-Dist: boto3 >=1.26.62
Requires-Dist: backoff >=1.10.0
Requires-Dist: requests >=2.22.0
Requires-Dist: rollbar >=0.14.7
Requires-Dist: xmltodict >=0.13.0
